chase/__init__.py
chase/__main__.py
chase/chart.py
chase/chase.py
chase/cli.py
rlane_chase-1.0.4.dist-info/METADATA
rlane_chase-1.0.4.dist-info/WHEEL
rlane_chase-1.0.4.dist-info/entry_points.txt
rlane_chase-1.0.4.dist-info/licenses/LICENSE
rlane_chase-1.0.4.dist-info/RECORD
