Metadata-Version: 2.1
Name: rlane-chase
Version: 1.0.4
Summary: Process Chase Bank transaction files
Keywords: chase,python,banking,checking,credit-cards,graphs
Author-Email: Russel Lane <russel@rlane.com>
License: MIT
Classifier: Development Status :: 4 - Beta
Classifier: Intended Audience :: End Users/Desktop
Classifier: License :: OSI Approved :: MIT License
Classifier: Programming Language :: Python :: 3
Classifier: Topic :: Office/Business :: Financial
Project-URL: Homepage, https://github.com/russellane/chase
Requires-Python: >=3.10
Requires-Dist: matplotlib>=3.9.2
Requires-Dist: numpy>=2.1.3
Requires-Dist: pandas>=2.2.3
Requires-Dist: rlane-libcli>=1.0.8
